{
  "objects": [
    {
      "package": {
        "name": "passport-lds-io",
        "version": "2.0.2",
        "description": "Node.js / ExpressJS / PassportJS OAuth2 authentication strategy for connecting with LDS.org",
        "keywords": [
          "LDSAuth",
          "LDSConnect",
          "LDS-Connect",
          "LDSOrg",
          "LDS.org",
          "LDS",
          "OAuth2",
          "OAuth",
          "auth",
          "passport"
        ],
        "date": "2015-04-01T22:05:07.216Z",
        "links": {
          "npm": "https://www.npmjs.com/package/passport-lds-io",
          "homepage": "https://github.com/LDSorg/passport-lds-connect",
          "repository": "git://github.com/LDSorg/passport-lds-connect.git",
          "bugs": "https://github.com/LDSorg/passport-lds-connect/issues"
        }
      },
      "flags": {},
      "downloadCounts": {
        "last-day": 0,
        "last-week": 5,
        "last-month": 20
      },
      "interactionCounts": {
        "bookmarks": 4,
        "subscribers": 2,
        "forks": 0
      }
    },
    {
      "package": {
        "name": "passport-lds",
        "version": "1.2.0",
        "description": "Node.js / ExpressJS / PassportJS OAuth2 authentication strategy for connecting with LDS.org",
        "keywords": [
          "LDSAuth",
          "LDSConnect",
          "LDS-Connect",
          "LDSOrg",
          "LDS.org",
          "LDS",
          "OAuth2",
          "OAuth",
          "auth",
          "passport"
        ],
        "date": "2015-03-02T22:18:01.257Z",
        "links": {
          "npm": "https://www.npmjs.com/package/passport-lds",
          "homepage": "https://github.com/LDSorg/passport-lds-connect",
          "repository": "git://github.com/LDSorg/passport-lds-connect.git",
          "bugs": "https://github.com/LDSorg/passport-lds-connect/issues"
        }
      },
      "flags": {},
      "downloadCounts": {
        "last-day": 0,
        "last-week": 7,
        "last-month": 20
      },
      "interactionCounts": {
        "bookmarks": 4,
        "subscribers": 2,
        "forks": 0
      }
    },
    {
      "package": {
        "name": "passport-ldsauth",
        "version": "1.2.0",
        "description": "Node.js / ExpressJS / PassportJS OAuth2 authentication strategy for connecting with LDS.org",
        "keywords": [
          "LDSAuth",
          "LDSConnect",
          "LDS-Connect",
          "LDSOrg",
          "LDS.org",
          "LDS",
          "OAuth2",
          "OAuth",
          "auth",
          "passport"
        ],
        "date": "2015-03-02T22:18:08.549Z",
        "links": {
          "npm": "https://www.npmjs.com/package/passport-ldsauth",
          "homepage": "https://github.com/LDSorg/passport-lds-connect",
          "repository": "git://github.com/LDSorg/passport-lds-connect.git",
          "bugs": "https://github.com/LDSorg/passport-lds-connect/issues"
        }
      },
      "flags": {},
      "downloadCounts": {
        "last-day": 1,
        "last-week": 9,
        "last-month": 34
      },
      "interactionCounts": {
        "bookmarks": 4,
        "subscribers": 2,
        "forks": 0
      }
    },
    {
      "package": {
        "name": "passport-learningstudio",
        "version": "1.0.2",
        "description": "A Passport Strategy for Pearson's Learning Studio.",
        "keywords": [
          "passport",
          "strategy",
          "pearson",
          "learningstudio",
          "learning",
          "studio"
        ],
        "date": "2014-07-07T20:39:57.934Z",
        "links": {
          "npm": "https://www.npmjs.com/package/passport-learningstudio",
          "homepage": "https://github.com/PearsonAPI/passport-learningstudio",
          "repository": "git://github.com/PearsonAPI/passport-learningstudio.git",
          "bugs": "http://github.com/PearsonAPI/passport-learningstudio/issues"
        }
      },
      "flags": {},
      "downloadCounts": {
        "last-day": 0,
        "last-week": 1,
        "last-month": 5
      }
    },
    {
      "package": {
        "name": "passport-lims",
        "version": "0.1.1",
        "description": "Lims authentication strategy for Passport.",
        "keywords": [
          "lims",
          "passport",
          "auth",
          "authn",
          "authentication",
          "authz",
          "authorization",
          "oauth",
          "oauth2"
        ],
        "date": "2017-05-04T14:07:27.234Z",
        "links": {
          "npm": "https://www.npmjs.com/package/passport-lims",
          "homepage": "https://github.com/taoyuan/passport-lims#readme",
          "repository": "git://github.com/taoyuan/passport-lims.git",
          "bugs": "http://github.com/taoyuan/passport-lims/issues"
        }
      },
      "flags": {},
      "downloadCounts": {
        "last-day": 0,
        "last-week": 1,
        "last-month": 9
      },
      "interactionCounts": {
        "bookmarks": 0,
        "subscribers": 1,
        "forks": 0
      }
    },
    {
      "package": {
        "name": "passport-line-auth",
        "version": "0.2.9",
        "description": "Line Authentication Strategy for Passport",
        "keywords": [
          "line",
          "passport",
          "identity",
          "auth",
          "authentication"
        ],
        "date": "2020-10-06T02:54:38.384Z",
        "links": {
          "npm": "https://www.npmjs.com/package/passport-line-auth",
          "homepage": "https://github.com/IvanWei/passport-line-auth#readme",
          "repository": "git+ssh://git@github.com/IvanWei/passport-line-auth.git",
          "bugs": "https://github.com/IvanWei/passport-line-auth/issues"
        }
      },
      "flags": {},
      "downloadCounts": {
        "last-day": 5,
        "last-week": 229,
        "last-month": 1102
      },
      "interactionCounts": {
        "bookmarks": 31,
        "subscribers": 1,
        "forks": 14
      }
    },
    {
      "package": {
        "name": "passport-line-v2",
        "version": "3.0.0",
        "description": "passport strategy for line",
        "keywords": [
          "passport-line",
          "line",
          "passport"
        ],
        "date": "2017-05-09T15:09:00.936Z",
        "links": {
          "npm": "https://www.npmjs.com/package/passport-line-v2",
          "homepage": "https://github.com/piggyman007/passport-line#readme",
          "repository": "git+https://github.com/piggyman007/passport-line.git",
          "bugs": "https://github.com/piggyman007/passport-line/issues"
        }
      },
      "flags": {},
      "downloadCounts": {
        "last-day": 1,
        "last-week": 36,
        "last-month": 210
      },
      "interactionCounts": {
        "bookmarks": 2,
        "subscribers": 1,
        "forks": 2
      }
    },
    {
      "package": {
        "name": "passport-line",
        "version": "0.0.4",
        "description": "LINE authentication strategy for Passport.",
        "keywords": [
          "passport",
          "line",
          "auth",
          "authn",
          "authentication",
          "identity"
        ],
        "date": "2018-05-07T08:30:03.135Z",
        "links": {
          "npm": "https://www.npmjs.com/package/passport-line",
          "homepage": "https://github.com/nitzo/passport-line",
          "repository": "git://github.com/nitzo/passport-line.git",
          "bugs": "http://github.com/nitzo/passport-line/issues"
        }
      },
      "flags": {},
      "downloadCounts": {
        "last-day": 7,
        "last-week": 416,
        "last-month": 12462
      },
      "interactionCounts": {
        "bookmarks": 11,
        "subscribers": 3,
        "forks": 7
      }
    },
    {
      "package": {
        "name": "passport-line2",
        "version": "1.0.0",
        "description": "Passport Line 2 Authentication Strategy for Passport",
        "keywords": [
          "line",
          "passport"
        ],
        "date": "2017-10-29T09:01:29.057Z",
        "links": {
          "npm": "https://www.npmjs.com/package/passport-line2",
          "homepage": "https://github.com/madeinfree/passport-line2#readme",
          "repository": "git+ssh://git@github.com/madeinfree/passport-line2.git",
          "bugs": "https://github.com/madeinfree/passport-line2/issues"
        }
      },
      "flags": {},
      "downloadCounts": {
        "last-day": 2,
        "last-week": 24,
        "last-month": 178
      },
      "interactionCounts": {
        "bookmarks": 1,
        "subscribers": 1,
        "forks": 1
      }
    },
    {
      "package": {
        "name": "passport-linkedin-oauth2",
        "version": "2.0.0",
        "description": "Passport for LinkedIn OAuth2 API v2",
        "keywords": [
          "passport",
          "linkedin",
          "auth0"
        ],
        "date": "2019-05-30T12:53:51.937Z",
        "links": {
          "npm": "https://www.npmjs.com/package/passport-linkedin-oauth2",
          "homepage": "https://github.com/auth0/passport-linkedin-oauth2#readme",
          "repository": "git+https://github.com/auth0/passport-linkedin-oauth2.git",
          "bugs": "https://github.com/auth0/passport-linkedin-oauth2/issues"
        }
      },
      "flags": {},
      "downloadCounts": {
        "last-day": 624,
        "last-week": 8501,
        "last-month": 46333
      },
      "interactionCounts": {
        "bookmarks": 103,
        "subscribers": 13,
        "forks": 89
      }
    },
    {
      "package": {
        "name": "passport-linkedin",
        "version": "1.0.0",
        "description": "LinkedIn authentication strategy for Passport.",
        "keywords": [
          "passport",
          "linkedin",
          "auth",
          "authn",
          "authentication",
          "identity"
        ],
        "date": "2015-09-14T23:50:19.681Z",
        "links": {
          "npm": "https://www.npmjs.com/package/passport-linkedin",
          "homepage": "https://github.com/jaredhanson/passport-linkedin",
          "repository": "git://github.com/jaredhanson/passport-linkedin.git",
          "bugs": "http://github.com/jaredhanson/passport-linkedin/issues"
        }
      },
      "flags": {},
      "downloadCounts": {
        "last-day": 163,
        "last-week": 1701,
        "last-month": 8950
      },
      "interactionCounts": {
        "bookmarks": 142,
        "subscribers": 9,
        "forks": 70
      }
    },
    {
      "package": {
        "name": "passport-liondesk",
        "version": "1.0.0",
        "description": "LionDesk (OAuth 2.0) authentication strategy for Passport.",
        "keywords": [
          "passport",
          "liondesk",
          "auth",
          "authn",
          "authentication",
          "identity"
        ],
        "date": "2018-09-22T17:51:31.583Z",
        "links": {
          "npm": "https://www.npmjs.com/package/passport-liondesk",
          "homepage": "https://github.com/chrux/passport-liondesk#readme",
          "repository": "git://github.com/chrux/passport-liondesk.git",
          "bugs": "http://github.com/chrux/passport-liondesk/issues"
        }
      },
      "flags": {},
      "downloadCounts": {
        "last-day": 0,
        "last-week": 1,
        "last-month": 4
      },
      "interactionCounts": {
        "bookmarks": 1,
        "subscribers": 2,
        "forks": 0
      }
    },
    {
      "package": {
        "name": "passport-lnurl-auth",
        "version": "1.4.2",
        "description": "Passport strategy that uses lnurl-auth",
        "keywords": [
          "passport",
          "strategy",
          "lnurl-auth",
          "lnurl",
          "auth"
        ],
        "date": "2021-10-28T14:12:21.551Z",
        "links": {
          "npm": "https://www.npmjs.com/package/passport-lnurl-auth",
          "homepage": "https://github.com/chill117/passport-lnurl-auth#readme",
          "repository": "git+https://github.com/chill117/passport-lnurl-auth.git",
          "bugs": "https://github.com/chill117/passport-lnurl-auth/issues"
        }
      },
      "flags": {},
      "downloadCounts": {
        "last-day": 0,
        "last-week": 10,
        "last-month": 27
      },
      "interactionCounts": {
        "bookmarks": 25,
        "subscribers": 2,
        "forks": 4
      }
    },
    {
      "package": {
        "name": "passport-local-htpasswd",
        "version": "0.1.1",
        "description": "Local username and password authentication strategy for Passport.",
        "keywords": [
          "passport",
          "local",
          "auth",
          "authn",
          "authentication",
          "username",
          "password",
          "htpasswd"
        ],
        "date": "2017-07-06T14:43:34.362Z",
        "links": {
          "npm": "https://www.npmjs.com/package/passport-local-htpasswd",
          "homepage": "https://github.com/morungos/passport-local-htpasswd#readme",
          "repository": "git://github.com/morungos/passport-local-htpasswd.git",
          "bugs": "http://github.com/morungos/passport-local-htpasswd/issues"
        }
      },
      "flags": {},
      "downloadCounts": {
        "last-day": 5,
        "last-week": 13,
        "last-month": 51
      },
      "interactionCounts": {
        "bookmarks": 3,
        "subscribers": 2,
        "forks": 0
      }
    },
    {
      "package": {
        "name": "passport-local-token",
        "version": "1.0.1",
        "description": "Local token authentication strategy for Passport.",
        "keywords": [
          "passport",
          "local",
          "auth",
          "authn",
          "authentication",
          "token"
        ],
        "date": "2014-10-18T13:58:29.689Z",
        "links": {
          "npm": "https://www.npmjs.com/package/passport-local-token",
          "homepage": "https://github.com/pferretti/passport-local-token",
          "repository": "git://github.com/pferretti/passport-local-token.git",
          "bugs": "http://github.com/pferretti/passport-local-token/issues"
        }
      },
      "flags": {},
      "downloadCounts": {
        "last-day": 1,
        "last-week": 79,
        "last-month": 616
      }
    },
    {
      "package": {
        "name": "passport-local",
        "version": "1.0.0",
        "description": "Local username and password authentication strategy for Passport.",
        "keywords": [
          "passport",
          "local",
          "auth",
          "authn",
          "authentication",
          "username",
          "password"
        ],
        "date": "2014-03-08T19:05:10.745Z",
        "links": {
          "npm": "https://www.npmjs.com/package/passport-local",
          "repository": "git://github.com/jaredhanson/passport-local.git",
          "bugs": "http://github.com/jaredhanson/passport-local/issues"
        }
      },
      "flags": {},
      "downloadCounts": {
        "last-day": 26401,
        "last-week": 310343,
        "last-month": 1826660
      },
      "interactionCounts": {
        "bookmarks": 2548,
        "subscribers": 55,
        "forks": 518
      }
    },
    {
      "package": {
        "name": "passport-localapikey",
        "version": "0.0.3",
        "description": "Local api key authentication strategy for Passport.",
        "date": "2012-12-08T06:02:45.048Z",
        "links": {
          "npm": "https://www.npmjs.com/package/passport-localapikey",
          "repository": "git://github.com/cholalabs/passport-localapikey.git"
        }
      },
      "flags": {},
      "downloadCounts": {
        "last-day": 63,
        "last-week": 736,
        "last-month": 4716
      },
      "interactionCounts": {
        "bookmarks": 162,
        "subscribers": 8,
        "forks": 56
      }
    },
    {
      "package": {
        "name": "passport-lti",
        "version": "0.0.7",
        "description": "Passport-based LTI authorization",
        "keywords": [
          "passport",
          "strategy",
          "lti"
        ],
        "date": "2016-08-12T15:18:54.187Z",
        "links": {
          "npm": "https://www.npmjs.com/package/passport-lti",
          "homepage": "https://github.com/civitaslearning/passport-lti",
          "repository": "git://github.com/civitaslearning/passport-lti.git",
          "bugs": "http://github.com/civitaslearning/passport-lti/issues"
        }
      },
      "flags": {},
      "downloadCounts": {
        "last-day": 9,
        "last-week": 244,
        "last-month": 2256
      },
      "interactionCounts": {
        "bookmarks": 26,
        "subscribers": 93,
        "forks": 11
      }
    },
    {
      "package": {
        "name": "passport-lyft",
        "version": "0.1.2",
        "description": "Lyft authentication strategy for Passport",
        "keywords": [
          "passport",
          "lyft",
          "auth",
          "oauth",
          "oauth2"
        ],
        "date": "2016-07-20T16:20:13.809Z",
        "links": {
          "npm": "https://www.npmjs.com/package/passport-lyft",
          "homepage": "https://github.com/girliemac/passport-lyft#readme",
          "repository": "git+https://github.com/girliemac/passport-lyft.git",
          "bugs": "https://github.com/girliemac/passport-lyft/issues"
        }
      },
      "flags": {},
      "downloadCounts": {
        "last-day": 0,
        "last-week": 7,
        "last-month": 13
      },
      "interactionCounts": {
        "bookmarks": 3,
        "subscribers": 0,
        "forks": 4
      }
    },
    {
      "package": {
        "name": "passport-mail",
        "version": "1.0.1",
        "description": "Mail ru authentication strategy for Passport.",
        "keywords": [
          "passport",
          "mail",
          "mailru",
          "mail-ru",
          "passport mailru",
          "passport mail-ru",
          "auth",
          "authn",
          "authentication",
          "identity"
        ],
        "date": "2016-04-09T06:35:27.031Z",
        "links": {
          "npm": "https://www.npmjs.com/package/passport-mail",
          "homepage": "https://github.com/sklyukin/passport-mailru#readme",
          "repository": "git://github.com/sklyukin/passport-mailru.git",
          "bugs": "http://github.com/sklyukin/passport-mailru/issues"
        }
      },
      "flags": {},
      "downloadCounts": {
        "last-day": 0,
        "last-week": 48,
        "last-month": 285
      },
      "interactionCounts": {
        "bookmarks": 1,
        "subscribers": 1,
        "forks": 1
      }
    },
    {
      "package": {
        "name": "passport-mailchimp",
        "version": "1.1.0",
        "description": "Mailchimp authentication strategy for Passport.",
        "keywords": [
          "mailchimp",
          "passport",
          "auth",
          "authentication"
        ],
        "date": "2016-11-23T06:38:11.513Z",
        "links": {
          "npm": "https://www.npmjs.com/package/passport-mailchimp",
          "repository": "https://github.com/brainflake/passport-mailchimp"
        }
      },
      "flags": {},
      "downloadCounts": {
        "last-day": 25,
        "last-week": 374,
        "last-month": 3011
      },
      "interactionCounts": {
        "bookmarks": 9,
        "subscribers": 3,
        "forks": 3
      }
    },
    {
      "package": {
        "name": "passport-mailru",
        "version": "0.0.1",
        "description": "Mail.ru authentication strategy for Passport.",
        "date": "2012-12-02T14:48:44.500Z",
        "links": {
          "npm": "https://www.npmjs.com/package/passport-mailru",
          "repository": "https://github.com/tiberule/passport-mailru"
        }
      },
      "flags": {},
      "downloadCounts": {
        "last-day": 1,
        "last-week": 14,
        "last-month": 46
      },
      "interactionCounts": {
        "bookmarks": 0,
        "subscribers": 1,
        "forks": 1
      }
    },
    {
      "package": {
        "name": "passport-makerpass",
        "version": "2.0.0",
        "description": "MakerPass authentication strategy for Passport.",
        "keywords": [
          "passport",
          "makerpass",
          "auth",
          "authn",
          "authentication",
          "identity"
        ],
        "date": "2015-11-04T21:23:31.235Z",
        "links": {
          "npm": "https://www.npmjs.com/package/passport-makerpass",
          "homepage": "https://github.com/makerpass/passport-makerpass#readme",
          "repository": "git+ssh://git@github.com/makerpass/passport-makerpass.git",
          "bugs": "http://github.com/makerpass/passport-makerpass/issues"
        }
      },
      "flags": {},
      "downloadCounts": {
        "last-day": 0,
        "last-week": 5,
        "last-month": 13
      }
    },
    {
      "package": {
        "name": "passport-maltio",
        "version": "1.0.0",
        "description": "Malt.io (OAuth2) authentication strategy for Passport.js",
        "date": "2013-07-28T02:20:01.689Z",
        "links": {
          "npm": "https://www.npmjs.com/package/passport-maltio",
          "repository": "https://github.com/homebrewing/passport-maltio"
        }
      },
      "flags": {},
      "downloadCounts": {
        "last-day": 1,
        "last-week": 4,
        "last-month": 15
      },
      "interactionCounts": {
        "bookmarks": 2,
        "subscribers": 3,
        "forks": 0
      }
    },
    {
      "package": {
        "name": "passport-mapmyfitness",
        "version": "1.0.3",
        "description": "Map my api authentication strategy for Passport.",
        "keywords": [
          "passport",
          "mapmyapi",
          "auth",
          "authn",
          "authentication",
          "identity"
        ],
        "date": "2014-11-25T22:34:11.413Z",
        "links": {
          "npm": "https://www.npmjs.com/package/passport-mapmyfitness",
          "homepage": "https://github.com/patbonecrusher/passport-mapmyfitness",
          "repository": "git://github.com/patbonecrusher/passport-mapmyfitness.git",
          "bugs": "http://github.com/patbonecrusher/passport-mapmyfitness/issues"
        }
      },
      "flags": {},
      "downloadCounts": {
        "last-day": 0,
        "last-week": 1,
        "last-month": 7
      },
      "interactionCounts": {
        "bookmarks": 0,
        "subscribers": 0,
        "forks": 2
      }
    }
  ],
  "total": 534,
  "urls": {
    "next": "/packages/-/v1/all/12.json",
    "prev": "/packages/-/v1/all/10.json"
  }
}